.coverage
.coveragerc
.gitignore
.travis.yml
AUTHORS
CONTRIBUTING.md
LICENSE
MANIFEST.in
NEWS.txt
README.rst
coverage.xml
errors.txt
official-cpe-dictionary_v2.3.xml
parser23.py
setup.cfg
setup.py
tox.ini
cpe/__init__.py
cpe/__meta__.py
cpe/cpe.py
cpe/cpe1_1.py
cpe/cpe2_2.py
cpe/cpe2_3.py
cpe/cpe2_3_fs.py
cpe/cpe2_3_uri.py
cpe/cpe2_3_wfn.py
cpe/cpelang.py
cpe/cpelang2_2.py
cpe/cpelang2_3.py
cpe/cpeset.py
cpe/cpeset1_1.py
cpe/cpeset2_2.py
cpe/cpeset2_3.py
cpe.egg-info/PKG-INFO
cpe.egg-info/SOURCES.txt
cpe.egg-info/dependency_links.txt
cpe.egg-info/top_level.txt
cpe/comp/__init__.py
cpe/comp/cpecomp.py
cpe/comp/cpecomp1_1.py
cpe/comp/cpecomp2_2.py
cpe/comp/cpecomp2_3.py
cpe/comp/cpecomp2_3_fs.py
cpe/comp/cpecomp2_3_uri.py
cpe/comp/cpecomp2_3_uri_edpacked.py
cpe/comp/cpecomp2_3_wfn.py
cpe/comp/cpecomp_anyvalue.py
cpe/comp/cpecomp_empty.py
cpe/comp/cpecomp_logical.py
cpe/comp/cpecomp_notapplicable.py
cpe/comp/cpecomp_simple.py
cpe/comp/cpecomp_undefined.py
docs/Makefile
docs/bugtracker.rst
docs/compatibility.rst
docs/conf.py
docs/cpeversions.rst
docs/examples.rst
docs/index.rst
docs/install.rst
docs/intro.rst
docs/issues.rst
docs/make.bat
docs/model.rst
docs/references.rst
docs/todo.rst
docs/_static/cpe_logo.gif
docs/_static/matching.png
docs/_static/cpe/cpe_model_all.png
docs/_static/cpe/cpe_model_all.pyns
docs/_static/cpe/cpe_model_all.pyns.pdf
docs/_static/cpe/cpe_model_public.png
docs/_static/cpe/cpe_model_public.pyns
docs/_static/cpe/cpe_model_public.pyns.pdf
docs/_static/cpecomp/cpecomp_model_all.png
docs/_static/cpecomp/cpecomp_model_all.pyns
docs/_static/cpecomp/cpecomp_model_all.pyns.pdf
docs/_static/cpecomp/cpecomp_model_public.png
docs/_static/cpecomp/cpecomp_model_public.pyns
docs/_static/cpecomp/cpecomp_model_public.pyns.pdf
docs/_static/cpelang/cpelang_model_all.png
docs/_static/cpelang/cpelang_model_all.pyns
docs/_static/cpelang/cpelang_model_all.pyns.pdf
docs/_static/cpelang/cpelang_model_public.png
docs/_static/cpelang/cpelang_model_public.pyns
docs/_static/cpelang/cpelang_model_public.pyns.pdf
docs/_static/cpeset/cpeset_model_all.png
