Metadata-Version: 1.1
Name: cpe
Version: 1.2.0
Summary: CPE: Common Platform Enumeration for Python
Home-page: https://github.com/nilp0inter/cpe
Author: Roberto Abdelkader Martínez Pérez
Author-email: robertomartinezp@gmail.com
License: LGPLv3
Keywords: c,p,e, ,i,d,e,n,t,i,f,i,c,a,t,i,o,n, ,n,a,m,i,n,g, ,m,a,t,c,h,i,n,g, ,s,t,a,n,d,a,r,d, ,s,p,e,c,i,f,i,c,a,t,i,o,n, ,m,i,t,r,e, ,n,i,s,t
Platform: UNKNOWN
Classifier: Development Status :: 5 - Production/Stable
Classifier: Intended Audience :: Developers
Classifier: Intended Audience :: Information Technology
Classifier: Intended Audience :: System Administrators
Classifier: License :: OSI Approved :: GNU Lesser General Public License v3 (LGPLv3)
Classifier: Natural Language :: English
Classifier: Operating System :: OS Independent
Classifier: Programming Language :: Python :: 2.7
